contact_notes_local/__init__.py
contact_notes_local/contact_notes_local.py
contact_notes_local/contact_notes_local_constants.py
contact_notes_local-0.0.55.dist-info/METADATA
contact_notes_local-0.0.55.dist-info/WHEEL
contact_notes_local-0.0.55.dist-info/top_level.txt
contact_notes_local-0.0.55.dist-info/RECORD
