Metadata-Version: 2.1
Name: contact-notes-local
Version: 0.0.55
Summary: PyPI Package for Circles contact-notes-local Python
Home-page: https://github.com/circles-zone/contact-notes-local-python-package
Author: Circles
Author-email: info@circlez.ai
Classifier: Programming Language :: Python :: 3
Classifier: License :: Other/Proprietary License
Classifier: Operating System :: OS Independent
Requires-Dist: database-infrastructure-local >=0.0.20
Requires-Dist: text-block-local >=0.0.9
Requires-Dist: contact-group-local >=0.0.7
Requires-Dist: action-items-local >=0.0.1
Requires-Dist: logger-local >=0.0.135
Requires-Dist: user-context-remote >=0.0.75
Requires-Dist: database-mysql-local >=0.0.290
Requires-Dist: profile-local >=0.0.61
Requires-Dist: language-remote >=0.0.20
